[
{"opis_pelny":"Status kombajnu","typ_danych":"Bit","jednostka":"_ALARM","grupa":"tab1status","id":"statusKombajnu","poz_ramka":0,"poz_bit":0},
{"typ_danych":"Bit","jednostka":"_Ostrzeżenie","grupa":"tab1status","id":"statusOstrzezenie","poz_ramka":0,"poz_bit":1},
{"opis_pelny":"Diagnostyka","typ_danych":"Bit","jednostka":"_BRAK BLOKAD","grupa":"tab1status","id":"diagnostykaBlokad","poz_ramka":0,"poz_bit":2},
{"typ_danych":"Bit","jednostka":"_Smar","grupa":"tab1status","id":"idTrwaSmarowanie","poz_ramka":0,"poz_bit":3},
{"typ_danych":"Bit","poz_ramka":0,"poz_bit":4},
{"typ_danych":"Bit","poz_ramka":0,"poz_bit":5},
{"typ_danych":"Bit","poz_ramka":0,"poz_bit":6},
{"typ_danych":"Bit","poz_ramka":0,"poz_bit":7},
{"typ_danych":"Bit","poz_ramka":0,"poz_bit":8},
{"typ_danych":"Bit","poz_ramka":0,"poz_bit":9},
{"typ_danych":"Bit","poz_ramka":0,"poz_bit":10},
{"typ_danych":"Bit","poz_ramka":0,"poz_bit":11},
{"typ_danych":"Bit","poz_ramka":0,"poz_bit":12},
{"typ_danych":"Bit","poz_ramka":0,"poz_bit":13},
{"typ_danych":"Bit","poz_ramka":0,"poz_bit":14},
{"typ_danych":"Bit","poz_ramka":0,"poz_bit":15},
{"typ_danych":"Bit","grupa":"klawiszeLCD","id":"lewo","poz_ramka":1,"poz_bit":0},
{"typ_danych":"Bit","grupa":"klawiszeLCD","id":"prawo","poz_ramka":1,"poz_bit":1},
{"typ_danych":"Bit","grupa":"klawiszeLCD","id":"gora","poz_ramka":1,"poz_bit":2},
{"typ_danych":"Bit","grupa":"klawiszeLCD","id":"dol","poz_ramka":1,"poz_bit":3},
{"typ_danych":"Bit","grupa":"klawiszeLCD","id":"enTEr","poz_ramka":1,"poz_bit":4},
{"typ_danych":"Bit","grupa":"klawiszeLCD","id":"EsCape","poz_ramka":1,"poz_bit":5},
{"typ_danych":"Bit","poz_ramka":1,"poz_bit":6},
{"typ_danych":"Bit","poz_ramka":1,"poz_bit":7},
{"typ_danych":"Bit","poz_ramka":1,"poz_bit":8},
{"typ_danych":"Bit","poz_ramka":1,"poz_bit":9},
{"typ_danych":"Bit","poz_ramka":1,"poz_bit":10},
{"typ_danych":"Bit","poz_ramka":1,"poz_bit":11},
{"typ_danych":"Bit","poz_ramka":1,"poz_bit":12},
{"typ_danych":"Bit","poz_ramka":1,"poz_bit":13},
{"typ_danych":"Bit","poz_ramka":1,"poz_bit":14},
{"typ_danych":"Bit","poz_ramka":1,"poz_bit":15},
{"opis_pelny":"Not-Aus","plc_nr":"PC1-A1","typ_danych":"Bit","jednostka":"DI","grupa":"tab1status","id":"idNotAus","poz_ramka":2,"poz_bit":0},
{"opis_pelny":"Załącz lokalnie","plc_nr":"PC1-A1","typ_danych":"Bit","jednostka":"DI","id":"idZalaczLokalnie","poz_ramka":2,"poz_bit":1},
{"opis_pelny":"Wyłącz","plc_nr":"PC1-A1","typ_danych":"Bit","jednostka":"DI","id":"idWylaczLokalnie","poz_ramka":2,"poz_bit":2},
{"opis_pelny":"Załącz / Wyłącz zdalnie","plc_nr":"PC1-A1","typ_danych":"Bit","jednostka":"DI","id":"idZalWylZdalnie","poz_ramka":2,"poz_bit":3},
{"opis_pelny":"Napęd główny załączony","plc_nr":"PC1-A1","typ_danych":"Bit","jednostka":"DI","grupa_2":"grafikaTab1","id":"idPotwZalNapedGlowny","poz_ramka":2,"poz_bit":4},
{"opis_pelny":"Silniki wibracyjne załączone","plc_nr":"PC1-A1","typ_danych":"Bit","jednostka":"DI","grupa_2":"grafikaTab1","id":"idPotwZalSilnikiWibracyjne","poz_ramka":2,"poz_bit":5,"ana_warn_h":"75","ana_alarm_h":"80","ana_max":"100","hist_LoALarm":"0","hist_HiALarm":"5"},
{"opis_pelny":"Silnik pompy smarowniczej załączony","plc_nr":"PC1-A1","typ_danych":"Bit","jednostka":"DI","grupa_2":"grafikaTab1","id":"idPotwZalSilnikPompySmar","poz_ramka":2,"poz_bit":6,"ana_warn_h":"75","ana_alarm_h":"80","ana_max":"100","hist_LoALarm":"0","hist_HiALarm":"5"},
{"opis_pelny":"Reset","plc_nr":"PC1-A1","typ_danych":"Bit","jednostka":"DI","grupa":"tab1status","id":"idReset","poz_ramka":2,"poz_bit":7,"ana_warn_h":"75","ana_alarm_h":"80","ana_max":"100","hist_LoALarm":"0","hist_HiALarm":"5"},
{"opis_pelny":"Klawiatura – Lewo","plc_nr":"PC1-A1","typ_danych":"Bit","jednostka":"DI","id":"idKlawiaturaLewo","poz_ramka":2,"poz_bit":8},
{"opis_pelny":"Klawiatura – Prawo","plc_nr":"PC1-A1","typ_danych":"Bit","jednostka":"DI","id":"idKlawiaturaPrawo","poz_ramka":2,"poz_bit":9},
{"opis_pelny":"Klawiatura – Góra","plc_nr":"PC1-A1","typ_danych":"Bit","jednostka":"DI","id":"idKlawiaturaGora","poz_ramka":2,"poz_bit":10},
{"opis_pelny":"Klawiatura – Dół","plc_nr":"PC1-A1","typ_danych":"Bit","jednostka":"DI","id":"idKlawiaturaDol","poz_ramka":2,"poz_bit":11},
{"opis_pelny":"Załącz pompkę smarowania","plc_nr":"PC1-A1","typ_danych":"Bit","jednostka":"DI","id":"idZalPompeSamrowania","poz_ramka":2,"poz_bit":12},
{"opis_pelny":"Poziomu smaru OK","plc_nr":"PC1-A1","typ_danych":"Bit","jednostka":"DI","id":"idPoziomSmaru","poz_ramka":2,"poz_bit":13},
{"opis_pelny":"Temperatura łożysk koła pasowego","plc_nr":"PC1-A2-A6","typ_danych":"Analog","jednostka":"°C","grupa":"temperaturyWOW","id":"idTempLozyskKoloPasowe","mnoznik":10,"poz_ramka":0,"wykresy":"tak","ana_min":"0","ana_alarm_l":"0","ana_warn_l":"0","ana_warn_h":"_par_rLozKoloPasowe_T_HiWr","ana_alarm_h":"_par_rLozKoloPasowe_T_HiAl","ana_max":"100","hist_LoALarm":"0","hist_HiALarm":"_par_rLozKoloPasowe_T_HiAlHist"},
{"opis_pelny":"Temperatura łożysk kosza sitowego","plc_nr":"PC1-A2-A6","typ_danych":"Analog","jednostka":"°C","grupa":"temperaturyWOW","id":"idTempLozyskKoszSitowy","mnoznik":10,"poz_ramka":1,"wykresy":"tak","ana_min":"0","ana_alarm_l":"0","ana_warn_l":"0","ana_warn_h":"_par_rLozKoszSitowy_T_HiWr","ana_alarm_h":"_par_rLozKoszSitowy_T_HiAl","ana_max":"100","hist_LoALarm":"0","hist_HiALarm":"_par_rLozKoszSitowy_T_HiAlHist"},
{"opis_pelny":"Temperatura silnika M1","plc_nr":"PC1-A2-A6","typ_danych":"Analog","jednostka":"°C","grupa":"temperaturyWOW","id":"idTempUzwojenM1","mnoznik":10,"poz_ramka":2,"wykresy":"tak","ana_min":"0","ana_alarm_l":"0","ana_warn_l":"0","ana_warn_h":"_par_rUzwNapGl_T_HiWr","ana_alarm_h":"_par_rUzwNapGl_T_HiAl","ana_max":"100","hist_LoALarm":"0","hist_HiALarm":"_par_rUzwNapGl_T_HiAlHist"},
{"opis_pelny":"Załącz silnik główny M1","plc_nr":"PC1-A2-A6","typ_danych":"Bit","jednostka":"DO","grupa_2":"grafikaTab1","id":"idZalaczM1","poz_ramka":3,"poz_bit":0},
{"opis_pelny":"Załącz silniki wibracyjne","plc_nr":"PC1-A2-A6","typ_danych":"Bit","jednostka":"DO","grupa_2":"grafikaTab1","id":"idZalaczWilnikiWibracyjne","poz_ramka":3,"poz_bit":1},
{"opis_pelny":"Załącz silnik pompy smarowaniaa","plc_nr":"PC1-A2-A6","typ_danych":"Bit","jednostka":"DO","grupa_2":"grafikaTab1","id":"idZalaczPompeSmarowania","poz_ramka":3,"poz_bit":2},
{"opis_pelny":"Sygnalizacja optyczna przycisk S2","plc_nr":"PC1-A2-A6","typ_danych":"Bit","jednostka":"DO","id":"idZalSygnOptS2","poz_ramka":3,"poz_bit":3},
{"opis_pelny":"Sygnał dźwiękowy BU1","plc_nr":"PC1-A2-A6","typ_danych":"Bit","jednostka":"DO","id":"idZalSygnDzwiek","poz_ramka":3,"poz_bit":4},
{"opis_pelny":"Sygnał świetlny BU1","plc_nr":"PC1-A2-A6","typ_danych":"Bit","jednostka":"DO","id":"idZalSygnKogut","poz_ramka":3,"poz_bit":5},
{"opis_pelny":"Miejsce sterowania","typ_danych":"Lista","jednostka":"_LOK","grupa":"tab1status","id":"miejsceSterowania","poz_ramka":3},
{"opis_pelny":"Licznik motogodzin","typ_danych":"Analog","jednostka":"h","grupa":"tab1status","id":"idLicznikMotoGodz","mnoznik":1,"poz_ramka":4},
{"opis_pelny":"Czas do smarowania","typ_danych":"Analog","jednostka":"min","grupa":"tab1status","id":"idCzasDoSmarowania","mnoznik":1,"poz_ramka":5},
{"opis_pelny":"Postęp smarowania","typ_danych":"Analog","jednostka":"%","grupa":"tab1status","id":"idPostepSamrowania","mnoznik":1,"poz_ramka":6},
{"opis_pelny":"Poziom smaru","typ_danych":"Bit","jednostka":"_OK","grupa":"tab1status","id":"idWOWPozSmaru","poz_ramka":2,"poz_bit":13},
{"opis_pelny":"Temp koła pas.","typ_danych":"Analog","jednostka":"°C","grupa":"tab1status","id":"idWOWtemKolPas","mnoznik":10,"poz_ramka":0},
{"opis_pelny":"Temp kosza sitow.","typ_danych":"Analog","jednostka":"°C","grupa":"tab1status","id":"idWOWtempKoszSit","mnoznik":10,"poz_ramka":1},
{"opis_pelny":"Temp silnika M1","typ_danych":"Analog","jednostka":"°C","grupa":"tab1status","id":"idWOWtempM1","mnoznik":10,"poz_ramka":2},
{}
]
